musicplayergui/__init__.py
musicplayergui-2.0.dist-info/METADATA
musicplayergui-2.0.dist-info/WHEEL
musicplayergui-2.0.dist-info/entry_points.txt
musicplayergui-2.0.dist-info/top_level.txt
musicplayergui-2.0.dist-info/RECORD
