Metadata-Version: 2.1
Name: musicplayergui
Version: 2.0
Summary: Random Music Player In form of GUI (So terrible GUI.)
Home-page: https://github.com/I-make-python-module-and-bots-stuff/Music-player
Author: Rukchad Wongprayoon
Author-email: mooping3roblox@gmail.com
License: MIT
Keywords: Tools
Platform: UNKNOWN
Requires-Dist: pygame
Requires-Dist: python-vlc
Requires-Dist: ffmpeg
Requires-Dist: youtube-dl
